iverilog/akhilTest/akhilTest.v
module akhilTest(A, B, C, D, X, Y);
   
   output X, Y;
   input  A, B, C, D;
   wire   w1, w2, w3, w4, w5;

   and G1(w1, A, B);
   or G2(w2, C, B);
   and G3(w3, C, D);
   and G4(w4, w1, w3);
   and G5(w5, w2, w3);
   or G6(X, w1, w4);
   and G7(Y, w3, w5);

  endmodule

iverilog/akhilTest/akhilTest_tb.v
`include "akhilTest.v"

module akhilTest_tb;

   wire A, B, C, D, X, Y;
   integer k=0;

   assign {A,B,C,D} = k;
   akhilTest wtfquestion(A, B, C, D, X, Y);

   initial begin

      $dumpfile("akhilTest.vcd");
      $dumpvars(0, akhilTest_tb);
      $monitor("A = %d, B = %d, C = %d, D = %d, X = %d, Y = %d",A, B, C, D, X, Y);

      for (k=0; k<16; k=k+1)
        #10;

      $finish;
   end

endmodule
a

iverilog/akhilTest/akhilTest.vcd
$date
	Sun Jul 03 18:10:57 2022
$end
$version
	Icarus Verilog
$end
$timescale
	1s
$end
$scope module akhilTest_tb $end
$var wire 1 ! Y $end
$var wire 1 " X $end
$var wire 1 # D $end
$var wire 1 $ C $end
$var wire 1 % B $end
$var wire 1 & A $end
$var integer 32 ' k [31:0] $end
$scope module wtfquestion $end
$var wire 1 & A $end
$var wire 1 % B $end
$var wire 1 $ C $end
$var wire 1 # D $end
$var wire 1 " X $end
$var wire 1 ! Y $end
$var wire 1 ( w1 $end
$var wire 1 ) w2 $end
$var wire 1 * w3 $end
$var wire 1 + w4 $end
$var wire 1 , w5 $end
$upscope $end
$upscope $end
$enddefinitions $end
#0
$dumpvars
0,
0+
0*
0)
0(
b0 '
0&
0%
0$
0#
0"
0!
$end
#10
1#
b1 '
#20
1)
0#
1$
b10 '
#30
1!
1,
1*
1#
b11 '
#40
0,
0!
0*
0#
0$
1%
b100 '
#50
1#
b101 '
#60
0#
1$
b110 '
#70
1!
1,
1*
1#
b111 '
#80
0!
0,
0*
0)
0#
0$
0%
1&
b1000 '
#90
1#
b1001 '
#100
1)
0#
1$
b1010 '
#110
1!
1,
1*
1#
b1011 '
#120
0,
0!
1"
0*
1(
0#
0$
1%
b1100 '
#130
1#
b1101 '
#140
0#
1$
b1110 '
#150
1!
1+
1,
1*
1#
b1111 '
#160
0"
0!
0,
0+
0*
0)
0(
0#
0$
0%
0&
b10000 '
