iverilog/behaviourModel/bcdTo7seg/7seg.v
//Verilog module.
module segment7(bcd, seg);
//Declare inputs,outputs and internal variables.
input [3:0] bcd;
output [6:0] seg;
reg [6:0] seg;
//always block for converting bcd digit into 7 segment format
always @(bcd)
begin
case (bcd) //case statement
0 : seg = 7'b0000001;
1 : seg = 7'b1001111;
2 : seg = 7'b0010010;
3 : seg = 7'b0000110;
4 : seg = 7'b1001100;
5 : seg = 7'b0100100;
6 : seg = 7'b0100000;
7 : seg = 7'b0001111;
8 : seg = 7'b0000000;
9 : seg = 7'b0000100;
//switch off 7 segment character when the bcd digit is not a decimal number.
default : seg = 7'b1111111;
endcase
end
endmodule

iverilog/behaviourModel/bcdTo7seg/7seg_tb.v
module tb_segment7;
reg [3:0] bcd;
wire [6:0] seg;
integer i;

segment7 uut (.bcd(bcd), .seg(seg));

initial begin
    $dumpfile("7seg.vcd");
    $dumpvars(0, tb_segment7);
    $monitor("%d : %7b" , bcd, seg);
    for(i = 0;i < 16;i = i+1)
    begin
        bcd = i;
        #10;
    end
end
endmodule

iverilog/behaviourModel/bcdTo7seg/7seg.vcd
$date
	Sun May 22 22:26:16 2022
$end
$version
	Icarus Verilog
$end
$timescale
	1s
$end
$scope module tb_segment7 $end
$var wire 7 ! seg [6:0] $end
$var reg 4 " bcd [3:0] $end
$var integer 32 # i [31:0] $end
$scope module uut $end
$var wire 4 $ bcd [3:0] $end
$var reg 7 % seg [6:0] $end
$upscope $end
$upscope $end
$enddefinitions $end
#0
$dumpvars
b1 %
b0 $
b0 #
b0 "
b1 !
$end
#10
b1001111 !
b1001111 %
b1 "
b1 $
b1 #
#20
b10010 !
b10010 %
b10 "
b10 $
b10 #
#30
b110 !
b110 %
b11 "
b11 $
b11 #
#40
b1001100 !
b1001100 %
b100 "
b100 $
b100 #
#50
b100100 !
b100100 %
b101 "
b101 $
b101 #
#60
b100000 !
b100000 %
b110 "
b110 $
b110 #
#70
b1111 !
b1111 %
b111 "
b111 $
b111 #
#80
b0 !
b0 %
b1000 "
b1000 $
b1000 #
#90
b100 !
b100 %
b1001 "
b1001 $
b1001 #
#100
b1111111 !
b1111111 %
b1010 "
b1010 $
b1010 #
#110
b1011 "
b1011 $
b1011 #
#120
b1100 "
b1100 $
b1100 #
#130
b1101 "
b1101 $
b1101 #
#140
b1110 "
b1110 $
b1110 #
#150
b1111 "
b1111 $
b1111 #
#160
b10000 #
